beepr/__init__.py
beepr/__main__.py
beepr/beep.py
beepr-0.1.2.dist-info/licenses/LICENSE
beepr-0.1.2.dist-info/METADATA
beepr-0.1.2.dist-info/WHEEL
beepr-0.1.2.dist-info/entry_points.txt
beepr-0.1.2.dist-info/top_level.txt
beepr-0.1.2.dist-info/RECORD
