Metadata-Version: 2.4
Name: beepr
Version: 0.1.2
Summary: A simple beeper CLI tool
Author-email: Nazarii Nyzhnyk <nazar.nyzhnyk@gmail.com>
License:                                  Apache License
Project-URL: Homepage, https://github.com/nazariinyzhnyk/beepr
Requires-Python: >=3.10
License-File: LICENSE
Dynamic: license-file
